SalesforceXytoolsCore/__init__.py
SalesforceXytoolsCore/__version__.py
SalesforceXytoolsCore/api.py
SalesforceXytoolsCore/bulk.py
SalesforceXytoolsCore/core.py
SalesforceXytoolsCore/login.py
SalesforceXytoolsCore/myconsole.py
SalesforceXytoolsCore/soap_envelopes.py
SalesforceXytoolsCore/util.py
SalesforceXytoolsCore/xmltodict.py
SalesforcexytoolsCore-2.1.dist-info/LICENSE.txt
SalesforcexytoolsCore-2.1.dist-info/METADATA
SalesforcexytoolsCore-2.1.dist-info/WHEEL
SalesforcexytoolsCore-2.1.dist-info/top_level.txt
SalesforcexytoolsCore-2.1.dist-info/RECORD
