Metadata-Version: 2.1
Name: SalesforcexytoolsCore
Version: 2.1
Summary: A basic Salesforce.com REST/Metadata/Soap API client. Base on simple-salesforce.
Home-page: http://salesforcexytools.com/Salesforce/SalesforceXyTools-For-Sublime.html
Author: Exia.Huang
Author-email: exia.huang@outlook.com
Maintainer: Exia.Huang
Maintainer-email: exia.huang@outlook.com
License: Apache 2.0
Keywords: python salesforce salesforce.com,rest,metadata,soap api
Platform: UNKNOWN
Classifier: Development Status :: 4 - Beta
Classifier: License :: OSI Approved :: Apache Software License
Classifier: Intended Audience :: Developers
Classifier: Intended Audience :: System Administrators
Classifier: Operating System :: OS Independent
Classifier: Topic :: Internet :: WWW/HTTP
Classifier: Programming Language :: Python :: 3.3
Classifier: Programming Language :: Python :: 3.4
Classifier: Programming Language :: Python :: 3.5
Classifier: Programming Language :: Python :: 3.6
Classifier: Programming Language :: Python :: Implementation :: PyPy
Requires-Dist: requests[security]
